{"config":{"output_file":null,"full_docs":false,"pub_only":false,"reachable_only":false,"distro_crate":false,"signatures":false,"borrow_data":false},"version":"0.19.0","compilation":{"directory":"/Users/dan/Documents/work/soedirgo.github.io","program":"/Users/dan/.rustup/toolchains/stable-x86_64-apple-darwin/bin/rls","arguments":[],"output":"/Users/dan/Documents/work/soedirgo.github.io/target/rls/debug/deps/liblife-3cc7d1551dd3e0bd.rmeta"},"prelude":{"crate_id":{"name":"life","disambiguator":[15197883927939447346,9242624848949257678]},"crate_root":"src","external_crates":[{"file_name":"/Users/dan/Documents/work/soedirgo.github.io/src/lib.rs","num":1,"id":{"name":"std","disambiguator":[15786589783347927115,14932276094748675792]}},{"file_name":"/Users/dan/Documents/work/soedirgo.github.io/src/lib.rs","num":2,"id":{"name":"core","disambiguator":[10298575208133357036,8040858178392247411]}},{"file_name":"/Users/dan/Documents/work/soedirgo.github.io/src/lib.rs","num":3,"id":{"name":"compiler_builtins","disambiguator":[12346914022686079705,4940267238012603511]}},{"file_name":"/Users/dan/Documents/work/soedirgo.github.io/src/lib.rs","num":4,"id":{"name":"rustc_std_workspace_core","disambiguator":[18114786932049689441,12972308710781110595]}},{"file_name":"/Users/dan/Documents/work/soedirgo.github.io/src/lib.rs","num":5,"id":{"name":"alloc","disambiguator":[3450676385096259377,17670937522874515785]}},{"file_name":"/Users/dan/Documents/work/soedirgo.github.io/src/lib.rs","num":6,"id":{"name":"libc","disambiguator":[17577124700929205618,18199936732272738370]}},{"file_name":"/Users/dan/Documents/work/soedirgo.github.io/src/lib.rs","num":7,"id":{"name":"unwind","disambiguator":[12559880231068804868,15252340553816167694]}},{"file_name":"/Users/dan/Documents/work/soedirgo.github.io/src/lib.rs","num":8,"id":{"name":"cfg_if","disambiguator":[1187771448540952860,5203397268813630476]}},{"file_name":"/Users/dan/Documents/work/soedirgo.github.io/src/lib.rs","num":9,"id":{"name":"backtrace","disambiguator":[18283159763238190815,6626693072124271590]}},{"file_name":"/Users/dan/Documents/work/soedirgo.github.io/src/lib.rs","num":10,"id":{"name":"rustc_demangle","disambiguator":[13458662043719537980,9570942752289014475]}},{"file_name":"/Users/dan/Documents/work/soedirgo.github.io/src/lib.rs","num":11,"id":{"name":"backtrace_sys","disambiguator":[11980204761434995587,1127255387257643439]}},{"file_name":"/Users/dan/Documents/work/soedirgo.github.io/src/lib.rs","num":12,"id":{"name":"hashbrown","disambiguator":[8467147480215253010,13194617755467267743]}},{"file_name":"/Users/dan/Documents/work/soedirgo.github.io/src/lib.rs","num":13,"id":{"name":"rustc_std_workspace_alloc","disambiguator":[8463084087322079994,16053869174229632260]}},{"file_name":"/Users/dan/Documents/work/soedirgo.github.io/src/lib.rs","num":14,"id":{"name":"panic_unwind","disambiguator":[16926090732921528503,7551031884587596916]}},{"file_name":"/Users/dan/Documents/work/soedirgo.github.io/src/lib.rs","num":15,"id":{"name":"wasm_bindgen","disambiguator":[10966264947720469355,4079415923404340169]}},{"file_name":"/Users/dan/Documents/work/soedirgo.github.io/src/lib.rs","num":16,"id":{"name":"wasm_bindgen_macro","disambiguator":[8288064959474296379,6019689241581181919]}},{"file_name":"/Users/dan/Documents/work/soedirgo.github.io/src/lib.rs","num":17,"id":{"name":"cfg_if","disambiguator":[3830940254276883228,8453204912267407483]}},{"file_name":"/Users/dan/Documents/work/soedirgo.github.io/src/utils.rs","num":18,"id":{"name":"console_error_panic_hook","disambiguator":[16819105186487693356,6616362873658064290]}}],"span":{"file_name":"src/lib.rs","byte_start":0,"byte_end":4637,"line_start":1,"line_end":192,"column_start":1,"column_end":2}},"imports":[{"kind":"GlobUse","ref_id":null,"span":{"file_name":"src/lib.rs","byte_start":39,"byte_end":40,"line_start":3,"line_end":3,"column_start":28,"column_end":29},"alias_span":null,"name":"*","value":"wasm_bindgen","parent":{"krate":0,"index":0}}],"defs":[{"kind":"Mod","id":{"krate":0,"index":0},"span":{"file_name":"src/lib.rs","byte_start":0,"byte_end":4637,"line_start":1,"line_end":192,"column_start":1,"column_end":2},"name":"","qualname":"::","value":"src/lib.rs","parent":null,"children":[{"krate":0,"index":1},{"krate":0,"index":2},{"krate":0,"index":3},{"krate":0,"index":5},{"krate":0,"index":27},{"krate":0,"index":43},{"krate":0,"index":42},{"krate":0,"index":40},{"krate":0,"index":37},{"krate":0,"index":38},{"krate":0,"index":34},{"krate":0,"index":35},{"krate":0,"index":14},{"krate":0,"index":17},{"krate":0,"index":20},{"krate":0,"index":22},{"krate":0,"index":24},{"krate":0,"index":45},{"krate":0,"index":49},{"krate":0,"index":53},{"krate":0,"index":58},{"krate":0,"index":65},{"krate":0,"index":68},{"krate":0,"index":72},{"krate":0,"index":76},{"krate":0,"index":78},{"krate":0,"index":6},{"krate":0,"index":80},{"krate":0,"index":9},{"krate":0,"index":12}],"decl_id":null,"docs":"","sig":null,"attributes":[]},{"kind":"Mod","id":{"krate":0,"index":3},"span":{"file_name":"src/utils.rs","byte_start":0,"byte_end":0,"line_start":1,"line_end":1,"column_start":1,"column_end":1},"name":"utils","qualname":"::utils","value":"src/utils.rs","parent":null,"children":[{"krate":0,"index":4}],"decl_id":null,"docs":"","sig":null,"attributes":[]},{"kind":"Function","id":{"krate":0,"index":4},"span":{"file_name":"src/utils.rs","byte_start":4646,"byte_end":4660,"line_start":1,"line_end":1,"column_start":8,"column_end":22},"name":"set_panic_hook","qualname":"::utils::set_panic_hook","value":"fn () -> ()","parent":null,"children":[],"decl_id":null,"docs":"","sig":null,"attributes":[]},{"kind":"TupleVariant","id":{"krate":0,"index":28},"span":{"file_name":"src/lib.rs","byte_start":338,"byte_end":342,"line_start":15,"line_end":15,"column_start":5,"column_end":9},"name":"Dead","qualname":"::Cell::Dead","value":"Cell::Dead","parent":{"krate":0,"index":27},"children":[],"decl_id":null,"docs":"","sig":null,"attributes":[]},{"kind":"TupleVariant","id":{"krate":0,"index":31},"span":{"file_name":"src/lib.rs","byte_start":352,"byte_end":357,"line_start":16,"line_end":16,"column_start":5,"column_end":10},"name":"Alive","qualname":"::Cell::Alive","value":"Cell::Alive","parent":{"krate":0,"index":27},"children":[],"decl_id":null,"docs":"","sig":null,"attributes":[]},{"kind":"Enum","id":{"krate":0,"index":27},"span":{"file_name":"src/lib.rs","byte_start":327,"byte_end":331,"line_start":14,"line_end":14,"column_start":10,"column_end":14},"name":"Cell","qualname":"::Cell","value":"Cell::{Dead, Alive}","parent":null,"children":[{"krate":0,"index":28},{"krate":0,"index":31}],"decl_id":null,"docs":"","sig":null,"attributes":[{"value":"repr(u8)","span":{"file_name":"src/lib.rs","byte_start":261,"byte_end":272,"line_start":12,"line_end":12,"column_start":1,"column_end":12}}]},{"kind":"Struct","id":{"krate":0,"index":45},"span":{"file_name":"src/lib.rs","byte_start":393,"byte_end":401,"line_start":20,"line_end":20,"column_start":12,"column_end":20},"name":"Universe","qualname":"::Universe","value":"Universe { width, height, cells }","parent":null,"children":[{"krate":0,"index":46},{"krate":0,"index":47},{"krate":0,"index":48}],"decl_id":null,"docs":"","sig":null,"attributes":[]},{"kind":"Field","id":{"krate":0,"index":46},"span":{"file_name":"src/lib.rs","byte_start":408,"byte_end":413,"line_start":21,"line_end":21,"column_start":5,"column_end":10},"name":"width","qualname":"::Universe::width","value":"u32","parent":{"krate":0,"index":45},"children":[],"decl_id":null,"docs":"","sig":null,"attributes":[]},{"kind":"Field","id":{"krate":0,"index":47},"span":{"file_name":"src/lib.rs","byte_start":424,"byte_end":430,"line_start":22,"line_end":22,"column_start":5,"column_end":11},"name":"height","qualname":"::Universe::height","value":"u32","parent":{"krate":0,"index":45},"children":[],"decl_id":null,"docs":"","sig":null,"attributes":[]},{"kind":"Field","id":{"krate":0,"index":48},"span":{"file_name":"src/lib.rs","byte_start":441,"byte_end":446,"line_start":23,"line_end":23,"column_start":5,"column_end":10},"name":"cells","qualname":"::Universe::cells","value":"std::vec::Vec<Cell>","parent":{"krate":0,"index":45},"children":[],"decl_id":null,"docs":"","sig":null,"attributes":[]},{"kind":"Local","id":{"krate":0,"index":4294967269},"span":{"file_name":"src/lib.rs","byte_start":496,"byte_end":500,"line_start":27,"line_end":27,"column_start":19,"column_end":23},"name":"self","qualname":"<Universe>::get_index::self","value":"&Universe","parent":null,"children":[],"decl_id":null,"docs":"","sig":null,"attributes":[]},{"kind":"Local","id":{"krate":0,"index":4294967265},"span":{"file_name":"src/lib.rs","byte_start":502,"byte_end":505,"line_start":27,"line_end":27,"column_start":25,"column_end":28},"name":"row","qualname":"<Universe>::get_index::row","value":"u32","parent":null,"children":[],"decl_id":null,"docs":"","sig":null,"attributes":[]},{"kind":"Local","id":{"krate":0,"index":4294967261},"span":{"file_name":"src/lib.rs","byte_start":512,"byte_end":518,"line_start":27,"line_end":27,"column_start":35,"column_end":41},"name":"column","qualname":"<Universe>::get_index::column","value":"u32","parent":null,"children":[],"decl_id":null,"docs":"","sig":null,"attributes":[]},{"kind":"Method","id":{"krate":0,"index":7},"span":{"file_name":"src/lib.rs","byte_start":485,"byte_end":494,"line_start":27,"line_end":27,"column_start":8,"column_end":17},"name":"get_index","qualname":"<Universe>::get_index","value":"fn (&self, row: u32, column: u32) -> usize","parent":null,"children":[],"decl_id":null,"docs":"","sig":null,"attributes":[]},{"kind":"Local","id":{"krate":0,"index":4294967241},"span":{"file_name":"src/lib.rs","byte_start":616,"byte_end":620,"line_start":31,"line_end":31,"column_start":29,"column_end":33},"name":"self","qualname":"<Universe>::live_neighbor_count::self","value":"&Universe","parent":null,"children":[],"decl_id":null,"docs":"","sig":null,"attributes":[]},{"kind":"Local","id":{"krate":0,"index":4294967237},"span":{"file_name":"src/lib.rs","byte_start":622,"byte_end":625,"line_start":31,"line_end":31,"column_start":35,"column_end":38},"name":"row","qualname":"<Universe>::live_neighbor_count::row","value":"u32","parent":null,"children":[],"decl_id":null,"docs":"","sig":null,"attributes":[]},{"kind":"Local","id":{"krate":0,"index":4294967233},"span":{"file_name":"src/lib.rs","byte_start":632,"byte_end":638,"line_start":31,"line_end":31,"column_start":45,"column_end":51},"name":"column","qualname":"<Universe>::live_neighbor_count::column","value":"u32","parent":null,"children":[],"decl_id":null,"docs":"","sig":null,"attributes":[]},{"kind":"Method","id":{"krate":0,"index":8},"span":{"file_name":"src/lib.rs","byte_start":595,"byte_end":614,"line_start":31,"line_end":31,"column_start":8,"column_end":27},"name":"live_neighbor_count","qualname":"<Universe>::live_neighbor_count","value":"fn (&self, row: u32, column: u32) -> u8","parent":null,"children":[],"decl_id":null,"docs":"","sig":null,"attributes":[]},{"kind":"Local","id":{"krate":0,"index":4294967226},"span":{"file_name":"src/lib.rs","byte_start":669,"byte_end":674,"line_start":32,"line_end":32,"column_start":17,"column_end":22},"name":"count","qualname":"count$69","value":"u8","parent":null,"children":[],"decl_id":null,"docs":"","sig":null,"attributes":[]},{"kind":"Local","id":{"krate":0,"index":4294967223},"span":{"file_name":"src/lib.rs","byte_start":693,"byte_end":698,"line_start":34,"line_end":34,"column_start":13,"column_end":18},"name":"north","qualname":"north$72","value":"u32","parent":null,"children":[],"decl_id":null,"docs":"","sig":null,"attributes":[]},{"kind":"Local","id":{"krate":0,"index":4294967204},"span":{"file_name":"src/lib.rs","byte_start":804,"byte_end":809,"line_start":40,"line_end":40,"column_start":13,"column_end":18},"name":"south","qualname":"south$91","value":"u32","parent":null,"children":[],"decl_id":null,"docs":"","sig":null,"attributes":[]},{"kind":"Local","id":{"krate":0,"index":4294967185},"span":{"file_name":"src/lib.rs","byte_start":915,"byte_end":919,"line_start":46,"line_end":46,"column_start":13,"column_end":17},"name":"west","qualname":"west$110","value":"u32","parent":null,"children":[],"decl_id":null,"docs":"","sig":null,"attributes":[]},{"kind":"Local","id":{"krate":0,"index":4294967166},"span":{"file_name":"src/lib.rs","byte_start":1030,"byte_end":1034,"line_start":52,"line_end":52,"column_start":13,"column_end":17},"name":"east","qualname":"east$129","value":"u32","parent":null,"children":[],"decl_id":null,"docs":"","sig":null,"attributes":[]},{"kind":"Local","id":{"krate":0,"index":4294967147},"span":{"file_name":"src/lib.rs","byte_start":1144,"byte_end":1146,"line_start":58,"line_end":58,"column_start":13,"column_end":15},"name":"nw","qualname":"nw$148","value":"usize","parent":null,"children":[],"decl_id":null,"docs":"","sig":null,"attributes":[]},{"kind":"Local","id":{"krate":0,"index":4294967125},"span":{"file_name":"src/lib.rs","byte_start":1230,"byte_end":1231,"line_start":61,"line_end":61,"column_start":13,"column_end":14},"name":"n","qualname":"n$170","value":"usize","parent":null,"children":[],"decl_id":null,"docs":"","sig":null,"attributes":[]},{"kind":"Local","id":{"krate":0,"index":4294967103},"span":{"file_name":"src/lib.rs","byte_start":1316,"byte_end":1318,"line_start":64,"line_end":64,"column_start":13,"column_end":15},"name":"ne","qualname":"ne$192","value":"usize","parent":null,"children":[],"decl_id":null,"docs":"","sig":null,"attributes":[]},{"kind":"Local","id":{"krate":0,"index":4294967081},"span":{"file_name":"src/lib.rs","byte_start":1402,"byte_end":1403,"line_start":67,"line_end":67,"column_start":13,"column_end":14},"name":"w","qualname":"w$214","value":"usize","parent":null,"children":[],"decl_id":null,"docs":"","sig":null,"attributes":[]},{"kind":"Local","id":{"krate":0,"index":4294967059},"span":{"file_name":"src/lib.rs","byte_start":1484,"byte_end":1485,"line_start":70,"line_end":70,"column_start":13,"column_end":14},"name":"e","qualname":"e$236","value":"usize","parent":null,"children":[],"decl_id":null,"docs":"","sig":null,"attributes":[]},{"kind":"Local","id":{"krate":0,"index":4294967037},"span":{"file_name":"src/lib.rs","byte_start":1566,"byte_end":1568,"line_start":73,"line_end":73,"column_start":13,"column_end":15},"name":"sw","qualname":"sw$258","value":"usize","parent":null,"children":[],"decl_id":null,"docs":"","sig":null,"attributes":[]},{"kind":"Local","id":{"krate":0,"index":4294967015},"span":{"file_name":"src/lib.rs","byte_start":1652,"byte_end":1653,"line_start":76,"line_end":76,"column_start":13,"column_end":14},"name":"s","qualname":"s$280","value":"usize","parent":null,"children":[],"decl_id":null,"docs":"","sig":null,"attributes":[]},{"kind":"Local","id":{"krate":0,"index":4294966993},"span":{"file_name":"src/lib.rs","byte_start":1738,"byte_end":1740,"line_start":79,"line_end":79,"column_start":13,"column_end":15},"name":"se","qualname":"se$302","value":"usize","parent":null,"children":[],"decl_id":null,"docs":"","sig":null,"attributes":[]},{"kind":"Local","id":{"krate":0,"index":4294966102},"span":{"file_name":"src/lib.rs","byte_start":1888,"byte_end":1892,"line_start":88,"line_end":88,"column_start":22,"column_end":26},"name":"self","qualname":"<Universe>::tick::self","value":"&mut Universe","parent":null,"children":[],"decl_id":null,"docs":"","sig":null,"attributes":[]},{"kind":"Method","id":{"krate":0,"index":81},"span":{"file_name":"src/lib.rs","byte_start":1878,"byte_end":1882,"line_start":88,"line_end":88,"column_start":12,"column_end":16},"name":"tick","qualname":"<Universe>::tick","value":"fn (&mut self) -> ()","parent":null,"children":[],"decl_id":null,"docs":"","sig":null,"attributes":[]},{"kind":"Local","id":{"krate":0,"index":4294966046},"span":{"file_name":"src/lib.rs","byte_start":1912,"byte_end":1916,"line_start":89,"line_end":89,"column_start":17,"column_end":21},"name":"next","qualname":"next$1249","value":"std::vec::Vec<Cell>","parent":null,"children":[],"decl_id":null,"docs":"","sig":null,"attributes":[]},{"kind":"Local","id":{"krate":0,"index":4294966037},"span":{"file_name":"src/lib.rs","byte_start":1990,"byte_end":1993,"line_start":94,"line_end":94,"column_start":17,"column_end":20},"name":"row","qualname":"row$1258","value":"u32","parent":null,"children":[],"decl_id":null,"docs":"","sig":null,"attributes":[]},{"kind":"Local","id":{"krate":0,"index":4294966030},"span":{"file_name":"src/lib.rs","byte_start":2034,"byte_end":2037,"line_start":95,"line_end":95,"column_start":21,"column_end":24},"name":"col","qualname":"col$1265","value":"u32","parent":null,"children":[],"decl_id":null,"docs":"","sig":null,"attributes":[]},{"kind":"Local","id":{"krate":0,"index":4294966022},"span":{"file_name":"src/lib.rs","byte_start":2081,"byte_end":2084,"line_start":96,"line_end":96,"column_start":25,"column_end":28},"name":"idx","qualname":"idx$1273","value":"usize","parent":null,"children":[],"decl_id":null,"docs":"","sig":null,"attributes":[]},{"kind":"Local","id":{"krate":0,"index":4294966012},"span":{"file_name":"src/lib.rs","byte_start":2137,"byte_end":2141,"line_start":97,"line_end":97,"column_start":25,"column_end":29},"name":"cell","qualname":"cell$1283","value":"Cell","parent":null,"children":[],"decl_id":null,"docs":"","sig":null,"attributes":[]},{"kind":"Local","id":{"krate":0,"index":4294966004},"span":{"file_name":"src/lib.rs","byte_start":2185,"byte_end":2199,"line_start":98,"line_end":98,"column_start":25,"column_end":39},"name":"live_neighbors","qualname":"live_neighbors$1291","value":"u8","parent":null,"children":[],"decl_id":null,"docs":"","sig":null,"attributes":[]},{"kind":"Local","id":{"krate":0,"index":4294965994},"span":{"file_name":"src/lib.rs","byte_start":2263,"byte_end":2272,"line_start":100,"line_end":100,"column_start":25,"column_end":34},"name":"next_cell","qualname":"next_cell$1301","value":"Cell","parent":null,"children":[],"decl_id":null,"docs":"","sig":null,"attributes":[]},{"kind":"Local","id":{"krate":0,"index":4294965983},"span":{"file_name":"src/lib.rs","byte_start":2397,"byte_end":2398,"line_start":102,"line_end":102,"column_start":39,"column_end":40},"name":"x","qualname":"x$1312","value":"u8","parent":null,"children":[],"decl_id":null,"docs":"","sig":null,"attributes":[]},{"kind":"Local","id":{"krate":0,"index":4294965953},"span":{"file_name":"src/lib.rs","byte_start":2645,"byte_end":2646,"line_start":106,"line_end":106,"column_start":39,"column_end":40},"name":"x","qualname":"x$1342","value":"u8","parent":null,"children":[],"decl_id":null,"docs":"","sig":null,"attributes":[]},{"kind":"Local","id":{"krate":0,"index":4294965933},"span":{"file_name":"src/lib.rs","byte_start":2867,"byte_end":2876,"line_start":110,"line_end":110,"column_start":26,"column_end":35},"name":"otherwise","qualname":"otherwise$1362","value":"Cell","parent":null,"children":[],"decl_id":null,"docs":"","sig":null,"attributes":[]},{"kind":"Local","id":{"krate":0,"index":4294965909},"span":{"file_name":"src/lib.rs","byte_start":3067,"byte_end":3071,"line_start":121,"line_end":121,"column_start":29,"column_end":33},"name":"self","qualname":"<Universe>::toggle_cell::self","value":"&mut Universe","parent":null,"children":[],"decl_id":null,"docs":"","sig":null,"attributes":[]},{"kind":"Local","id":{"krate":0,"index":4294965905},"span":{"file_name":"src/lib.rs","byte_start":3073,"byte_end":3076,"line_start":121,"line_end":121,"column_start":35,"column_end":38},"name":"row","qualname":"<Universe>::toggle_cell::row","value":"u32","parent":null,"children":[],"decl_id":null,"docs":"","sig":null,"attributes":[]},{"kind":"Local","id":{"krate":0,"index":4294965901},"span":{"file_name":"src/lib.rs","byte_start":3083,"byte_end":3089,"line_start":121,"line_end":121,"column_start":45,"column_end":51},"name":"column","qualname":"<Universe>::toggle_cell::column","value":"u32","parent":null,"children":[],"decl_id":null,"docs":"","sig":null,"attributes":[]},{"kind":"Method","id":{"krate":0,"index":83},"span":{"file_name":"src/lib.rs","byte_start":3050,"byte_end":3061,"line_start":121,"line_end":121,"column_start":12,"column_end":23},"name":"toggle_cell","qualname":"<Universe>::toggle_cell","value":"fn (&mut self, row: u32, column: u32) -> ()","parent":null,"children":[],"decl_id":null,"docs":"","sig":null,"attributes":[]},{"kind":"Local","id":{"krate":0,"index":4294965795},"span":{"file_name":"src/lib.rs","byte_start":3110,"byte_end":3113,"line_start":122,"line_end":122,"column_start":13,"column_end":16},"name":"idx","qualname":"idx$1500","value":"usize","parent":null,"children":[],"decl_id":null,"docs":"","sig":null,"attributes":[]},{"kind":"Method","id":{"krate":0,"index":85},"span":{"file_name":"src/lib.rs","byte_start":3197,"byte_end":3200,"line_start":126,"line_end":126,"column_start":12,"column_end":15},"name":"new","qualname":"<Universe>::new","value":"fn () -> Universe","parent":null,"children":[],"decl_id":null,"docs":"","sig":null,"attributes":[]},{"kind":"Local","id":{"krate":0,"index":4294965740},"span":{"file_name":"src/lib.rs","byte_start":3263,"byte_end":3268,"line_start":129,"line_end":129,"column_start":13,"column_end":18},"name":"width","qualname":"width$1555","value":"u32","parent":null,"children":[],"decl_id":null,"docs":"","sig":null,"attributes":[]},{"kind":"Local","id":{"krate":0,"index":4294965737},"span":{"file_name":"src/lib.rs","byte_start":3288,"byte_end":3294,"line_start":130,"line_end":130,"column_start":13,"column_end":19},"name":"height","qualname":"height$1558","value":"u32","parent":null,"children":[],"decl_id":null,"docs":"","sig":null,"attributes":[]},{"kind":"Local","id":{"krate":0,"index":4294965734},"span":{"file_name":"src/lib.rs","byte_start":3315,"byte_end":3320,"line_start":132,"line_end":132,"column_start":13,"column_end":18},"name":"cells","qualname":"cells$1561","value":"std::vec::Vec<Cell>","parent":null,"children":[],"decl_id":null,"docs":"","sig":null,"attributes":[]},{"kind":"Local","id":{"krate":0,"index":4294965723},"span":{"file_name":"src/lib.rs","byte_start":3361,"byte_end":3362,"line_start":133,"line_end":133,"column_start":19,"column_end":20},"name":"i","qualname":"$1599::i","value":"u32","parent":null,"children":[],"decl_id":null,"docs":"","sig":null,"attributes":[]},{"kind":"Local","id":{"krate":0,"index":4294965680},"span":{"file_name":"src/lib.rs","byte_start":3670,"byte_end":3674,"line_start":149,"line_end":149,"column_start":19,"column_end":23},"name":"self","qualname":"<Universe>::width::self","value":"&Universe","parent":null,"children":[],"decl_id":null,"docs":"","sig":null,"attributes":[]},{"kind":"Method","id":{"krate":0,"index":88},"span":{"file_name":"src/lib.rs","byte_start":3663,"byte_end":3668,"line_start":149,"line_end":149,"column_start":12,"column_end":17},"name":"width","qualname":"<Universe>::width","value":"fn (&self) -> u32","parent":null,"children":[],"decl_id":null,"docs":"","sig":null,"attributes":[]},{"kind":"Local","id":{"krate":0,"index":4294965616},"span":{"file_name":"src/lib.rs","byte_start":3730,"byte_end":3734,"line_start":153,"line_end":153,"column_start":20,"column_end":24},"name":"self","qualname":"<Universe>::height::self","value":"&Universe","parent":null,"children":[],"decl_id":null,"docs":"","sig":null,"attributes":[]},{"kind":"Method","id":{"krate":0,"index":90},"span":{"file_name":"src/lib.rs","byte_start":3722,"byte_end":3728,"line_start":153,"line_end":153,"column_start":12,"column_end":18},"name":"height","qualname":"<Universe>::height","value":"fn (&self) -> u32","parent":null,"children":[],"decl_id":null,"docs":"","sig":null,"attributes":[]},{"kind":"Local","id":{"krate":0,"index":4294965552},"span":{"file_name":"src/lib.rs","byte_start":3790,"byte_end":3794,"line_start":157,"line_end":157,"column_start":19,"column_end":23},"name":"self","qualname":"<Universe>::cells::self","value":"&Universe","parent":null,"children":[],"decl_id":null,"docs":"","sig":null,"attributes":[]},{"kind":"Method","id":{"krate":0,"index":92},"span":{"file_name":"src/lib.rs","byte_start":3783,"byte_end":3788,"line_start":157,"line_end":157,"column_start":12,"column_end":17},"name":"cells","qualname":"<Universe>::cells","value":"fn (&self) -> *const Cell","parent":null,"children":[],"decl_id":null,"docs":"","sig":null,"attributes":[]},{"kind":"Local","id":{"krate":0,"index":4294965483},"span":{"file_name":"src/lib.rs","byte_start":3874,"byte_end":3878,"line_start":161,"line_end":161,"column_start":27,"column_end":31},"name":"self","qualname":"<Universe>::set_width::self","value":"&mut Universe","parent":null,"children":[],"decl_id":null,"docs":"","sig":null,"attributes":[]},{"kind":"Local","id":{"krate":0,"index":4294965479},"span":{"file_name":"src/lib.rs","byte_start":3880,"byte_end":3885,"line_start":161,"line_end":161,"column_start":33,"column_end":38},"name":"width","qualname":"<Universe>::set_width::width","value":"u32","parent":null,"children":[],"decl_id":null,"docs":"","sig":null,"attributes":[]},{"kind":"Method","id":{"krate":0,"index":94},"span":{"file_name":"src/lib.rs","byte_start":3859,"byte_end":3868,"line_start":161,"line_end":161,"column_start":12,"column_end":21},"name":"set_width","qualname":"<Universe>::set_width","value":"fn (&mut self, width: u32) -> ()","parent":null,"children":[],"decl_id":null,"docs":"","sig":null,"attributes":[]},{"kind":"Local","id":{"krate":0,"index":4294965379},"span":{"file_name":"src/lib.rs","byte_start":3973,"byte_end":3975,"line_start":163,"line_end":163,"column_start":52,"column_end":54},"name":"_i","qualname":"$1921::_i","value":"u32","parent":null,"children":[],"decl_id":null,"docs":"","sig":null,"attributes":[]},{"kind":"Local","id":{"krate":0,"index":4294965368},"span":{"file_name":"src/lib.rs","byte_start":4034,"byte_end":4038,"line_start":166,"line_end":166,"column_start":28,"column_end":32},"name":"self","qualname":"<Universe>::set_height::self","value":"&mut Universe","parent":null,"children":[],"decl_id":null,"docs":"","sig":null,"attributes":[]},{"kind":"Local","id":{"krate":0,"index":4294965364},"span":{"file_name":"src/lib.rs","byte_start":4040,"byte_end":4046,"line_start":166,"line_end":166,"column_start":34,"column_end":40},"name":"height","qualname":"<Universe>::set_height::height","value":"u32","parent":null,"children":[],"decl_id":null,"docs":"","sig":null,"attributes":[]},{"kind":"Method","id":{"krate":0,"index":97},"span":{"file_name":"src/lib.rs","byte_start":4018,"byte_end":4028,"line_start":166,"line_end":166,"column_start":12,"column_end":22},"name":"set_height","qualname":"<Universe>::set_height","value":"fn (&mut self, height: u32) -> ()","parent":null,"children":[],"decl_id":null,"docs":"","sig":null,"attributes":[]},{"kind":"Local","id":{"krate":0,"index":4294965264},"span":{"file_name":"src/lib.rs","byte_start":4136,"byte_end":4138,"line_start":168,"line_end":168,"column_start":52,"column_end":54},"name":"_i","qualname":"$2036::_i","value":"u32","parent":null,"children":[],"decl_id":null,"docs":"","sig":null,"attributes":[]},{"kind":"Local","id":{"krate":0,"index":4294966965},"span":{"file_name":"src/lib.rs","byte_start":4210,"byte_end":4214,"line_start":173,"line_end":173,"column_start":23,"column_end":27},"name":"self","qualname":"<Universe>::get_cells::self","value":"&Universe","parent":null,"children":[],"decl_id":null,"docs":"","sig":null,"attributes":[]},{"kind":"Method","id":{"krate":0,"index":10},"span":{"file_name":"src/lib.rs","byte_start":4199,"byte_end":4208,"line_start":173,"line_end":173,"column_start":12,"column_end":21},"name":"get_cells","qualname":"<Universe>::get_cells","value":"fn (&self) -> &[Cell]","parent":null,"children":[],"decl_id":null,"docs":"","sig":null,"attributes":[]},{"kind":"Local","id":{"krate":0,"index":4294966951},"span":{"file_name":"src/lib.rs","byte_start":4282,"byte_end":4286,"line_start":177,"line_end":177,"column_start":27,"column_end":31},"name":"self","qualname":"<Universe>::set_cells::self","value":"&mut Universe","parent":null,"children":[],"decl_id":null,"docs":"","sig":null,"attributes":[]},{"kind":"Local","id":{"krate":0,"index":4294966947},"span":{"file_name":"src/lib.rs","byte_start":4288,"byte_end":4293,"line_start":177,"line_end":177,"column_start":33,"column_end":38},"name":"cells","qualname":"<Universe>::set_cells::cells","value":"&[(u32, u32)]","parent":null,"children":[],"decl_id":null,"docs":"","sig":null,"attributes":[]},{"kind":"Method","id":{"krate":0,"index":11},"span":{"file_name":"src/lib.rs","byte_start":4267,"byte_end":4276,"line_start":177,"line_end":177,"column_start":12,"column_end":21},"name":"set_cells","qualname":"<Universe>::set_cells","value":"fn (&mut self, cells: &[(u32, u32)]) -> ()","parent":null,"children":[],"decl_id":null,"docs":"","sig":null,"attributes":[]},{"kind":"Local","id":{"krate":0,"index":4294966937},"span":{"file_name":"src/lib.rs","byte_start":4325,"byte_end":4328,"line_start":178,"line_end":178,"column_start":14,"column_end":17},"name":"row","qualname":"row$358","value":"u32","parent":null,"children":[],"decl_id":null,"docs":"","sig":null,"attributes":[]},{"kind":"Local","id":{"krate":0,"index":4294966936},"span":{"file_name":"src/lib.rs","byte_start":4330,"byte_end":4333,"line_start":178,"line_end":178,"column_start":19,"column_end":22},"name":"col","qualname":"col$359","value":"u32","parent":null,"children":[],"decl_id":null,"docs":"","sig":null,"attributes":[]},{"kind":"Local","id":{"krate":0,"index":4294966927},"span":{"file_name":"src/lib.rs","byte_start":4378,"byte_end":4381,"line_start":179,"line_end":179,"column_start":17,"column_end":20},"name":"idx","qualname":"idx$368","value":"usize","parent":null,"children":[],"decl_id":null,"docs":"","sig":null,"attributes":[]},{"kind":"Local","id":{"krate":0,"index":4294966902},"span":{"file_name":"src/lib.rs","byte_start":4503,"byte_end":4507,"line_start":186,"line_end":186,"column_start":20,"column_end":24},"name":"self","qualname":"<Cell>::toggle::self","value":"&mut Cell","parent":null,"children":[],"decl_id":null,"docs":"","sig":null,"attributes":[]},{"kind":"Method","id":{"krate":0,"index":13},"span":{"file_name":"src/lib.rs","byte_start":4491,"byte_end":4497,"line_start":186,"line_end":186,"column_start":8,"column_end":14},"name":"toggle","qualname":"<Cell>::toggle","value":"fn (&mut self) -> ()","parent":null,"children":[],"decl_id":null,"docs":"","sig":null,"attributes":[]}],"impls":[{"id":12,"kind":"Inherent","span":{"file_name":"src/lib.rs","byte_start":467,"byte_end":475,"line_start":26,"line_end":26,"column_start":6,"column_end":14},"value":"","parent":null,"children":[{"krate":0,"index":7},{"krate":0,"index":8}],"docs":"","sig":null,"attributes":[]},{"id":13,"kind":"Inherent","span":{"file_name":"src/lib.rs","byte_start":1856,"byte_end":1864,"line_start":87,"line_end":87,"column_start":6,"column_end":14},"value":"","parent":null,"children":[{"krate":0,"index":81},{"krate":0,"index":83},{"krate":0,"index":85},{"krate":0,"index":88},{"krate":0,"index":90},{"krate":0,"index":92},{"krate":0,"index":94},{"krate":0,"index":97}],"docs":"","sig":null,"attributes":[]},{"id":14,"kind":"Inherent","span":{"file_name":"src/lib.rs","byte_start":4177,"byte_end":4185,"line_start":172,"line_end":172,"column_start":6,"column_end":14},"value":"","parent":null,"children":[{"krate":0,"index":10},{"krate":0,"index":11}],"docs":"","sig":null,"attributes":[]},{"id":15,"kind":"Inherent","span":{"file_name":"src/lib.rs","byte_start":4477,"byte_end":4481,"line_start":185,"line_end":185,"column_start":6,"column_end":10},"value":"","parent":null,"children":[{"krate":0,"index":13}],"docs":"","sig":null,"attributes":[]}],"refs":[{"kind":"Mod","span":{"file_name":"src/lib.rs","byte_start":4,"byte_end":9,"line_start":1,"line_end":1,"column_start":5,"column_end":10},"ref_id":{"krate":0,"index":3}},{"kind":"Function","span":{"file_name":"src/utils.rs","byte_start":5070,"byte_end":5078,"line_start":9,"line_end":9,"column_start":31,"column_end":39},"ref_id":{"krate":18,"index":6}},{"kind":"Mod","span":{"file_name":"src/utils.rs","byte_start":5044,"byte_end":5068,"line_start":9,"line_end":9,"column_start":5,"column_end":29},"ref_id":{"krate":18,"index":0}},{"kind":"Mod","span":{"file_name":"src/lib.rs","byte_start":16,"byte_end":28,"line_start":3,"line_end":3,"column_start":5,"column_end":17},"ref_id":{"krate":15,"index":0}},{"kind":"Mod","span":{"file_name":"src/lib.rs","byte_start":30,"byte_end":37,"line_start":3,"line_end":3,"column_start":19,"column_end":26},"ref_id":{"krate":15,"index":16}},{"kind":"Type","span":{"file_name":"src/lib.rs","byte_start":327,"byte_end":331,"line_start":14,"line_end":14,"column_start":10,"column_end":14},"ref_id":{"krate":0,"index":27}},{"kind":"Type","span":{"file_name":"src/lib.rs","byte_start":327,"byte_end":331,"line_start":14,"line_end":14,"column_start":10,"column_end":14},"ref_id":{"krate":0,"index":27}},{"kind":"Variable","span":{"file_name":"src/lib.rs","byte_start":338,"byte_end":342,"line_start":15,"line_end":15,"column_start":5,"column_end":9},"ref_id":{"krate":0,"index":29}},{"kind":"Type","span":{"file_name":"src/lib.rs","byte_start":327,"byte_end":331,"line_start":14,"line_end":14,"column_start":10,"column_end":14},"ref_id":{"krate":0,"index":27}},{"kind":"Variable","span":{"file_name":"src/lib.rs","byte_start":338,"byte_end":342,"line_start":15,"line_end":15,"column_start":5,"column_end":9},"ref_id":{"krate":0,"index":29}},{"kind":"Type","span":{"file_name":"src/lib.rs","byte_start":327,"byte_end":331,"line_start":14,"line_end":14,"column_start":10,"column_end":14},"ref_id":{"krate":0,"index":27}},{"kind":"Variable","span":{"file_name":"src/lib.rs","byte_start":352,"byte_end":357,"line_start":16,"line_end":16,"column_start":5,"column_end":10},"ref_id":{"krate":0,"index":32}},{"kind":"Type","span":{"file_name":"src/lib.rs","byte_start":327,"byte_end":331,"line_start":14,"line_end":14,"column_start":10,"column_end":14},"ref_id":{"krate":0,"index":27}},{"kind":"Variable","span":{"file_name":"src/lib.rs","byte_start":352,"byte_end":357,"line_start":16,"line_end":16,"column_start":5,"column_end":10},"ref_id":{"krate":0,"index":32}},{"kind":"Type","span":{"file_name":"src/lib.rs","byte_start":327,"byte_end":331,"line_start":14,"line_end":14,"column_start":10,"column_end":14},"ref_id":{"krate":0,"index":27}},{"kind":"Type","span":{"file_name":"src/lib.rs","byte_start":327,"byte_end":331,"line_start":14,"line_end":14,"column_start":10,"column_end":14},"ref_id":{"krate":0,"index":27}},{"kind":"Type","span":{"file_name":"src/lib.rs","byte_start":327,"byte_end":331,"line_start":14,"line_end":14,"column_start":10,"column_end":14},"ref_id":{"krate":0,"index":27}},{"kind":"Type","span":{"file_name":"src/lib.rs","byte_start":327,"byte_end":331,"line_start":14,"line_end":14,"column_start":10,"column_end":14},"ref_id":{"krate":0,"index":27}},{"kind":"Type","span":{"file_name":"src/lib.rs","byte_start":448,"byte_end":451,"line_start":23,"line_end":23,"column_start":12,"column_end":15},"ref_id":{"krate":5,"index":3846}},{"kind":"Type","span":{"file_name":"src/lib.rs","byte_start":452,"byte_end":456,"line_start":23,"line_end":23,"column_start":16,"column_end":20},"ref_id":{"krate":0,"index":27}},{"kind":"Type","span":{"file_name":"src/lib.rs","byte_start":393,"byte_end":401,"line_start":20,"line_end":20,"column_start":12,"column_end":20},"ref_id":{"krate":0,"index":45}},{"kind":"Type","span":{"file_name":"src/lib.rs","byte_start":393,"byte_end":401,"line_start":20,"line_end":20,"column_start":12,"column_end":20},"ref_id":{"krate":0,"index":45}},{"kind":"Type","span":{"file_name":"src/lib.rs","byte_start":393,"byte_end":401,"line_start":20,"line_end":20,"column_start":12,"column_end":20},"ref_id":{"krate":0,"index":45}},{"kind":"Type","span":{"file_name":"src/lib.rs","byte_start":393,"byte_end":401,"line_start":20,"line_end":20,"column_start":12,"column_end":20},"ref_id":{"krate":0,"index":45}},{"kind":"Type","span":{"file_name":"src/lib.rs","byte_start":393,"byte_end":401,"line_start":20,"line_end":20,"column_start":12,"column_end":20},"ref_id":{"krate":0,"index":45}},{"kind":"Type","span":{"file_name":"src/lib.rs","byte_start":393,"byte_end":401,"line_start":20,"line_end":20,"column_start":12,"column_end":20},"ref_id":{"krate":0,"index":45}},{"kind":"Type","span":{"file_name":"src/lib.rs","byte_start":393,"byte_end":401,"line_start":20,"line_end":20,"column_start":12,"column_end":20},"ref_id":{"krate":0,"index":45}},{"kind":"Type","span":{"file_name":"src/lib.rs","byte_start":393,"byte_end":401,"line_start":20,"line_end":20,"column_start":12,"column_end":20},"ref_id":{"krate":0,"index":45}},{"kind":"Type","span":{"file_name":"src/lib.rs","byte_start":467,"byte_end":475,"line_start":26,"line_end":26,"column_start":6,"column_end":14},"ref_id":{"krate":0,"index":45}},{"kind":"Variable","span":{"file_name":"src/lib.rs","byte_start":545,"byte_end":548,"line_start":28,"line_end":28,"column_start":10,"column_end":13},"ref_id":{"krate":0,"index":4294967265}},{"kind":"Variable","span":{"file_name":"src/lib.rs","byte_start":551,"byte_end":555,"line_start":28,"line_end":28,"column_start":16,"column_end":20},"ref_id":{"krate":0,"index":4294967269}},{"kind":"Variable","span":{"file_name":"src/lib.rs","byte_start":556,"byte_end":561,"line_start":28,"line_end":28,"column_start":21,"column_end":26},"ref_id":{"krate":0,"index":46}},{"kind":"Variable","span":{"file_name":"src/lib.rs","byte_start":564,"byte_end":570,"line_start":28,"line_end":28,"column_start":29,"column_end":35},"ref_id":{"krate":0,"index":4294967261}},{"kind":"Variable","span":{"file_name":"src/lib.rs","byte_start":704,"byte_end":707,"line_start":34,"line_end":34,"column_start":24,"column_end":27},"ref_id":{"krate":0,"index":4294967237}},{"kind":"Variable","span":{"file_name":"src/lib.rs","byte_start":727,"byte_end":731,"line_start":35,"line_end":35,"column_start":13,"column_end":17},"ref_id":{"krate":0,"index":4294967241}},{"kind":"Variable","span":{"file_name":"src/lib.rs","byte_start":732,"byte_end":738,"line_start":35,"line_end":35,"column_start":18,"column_end":24},"ref_id":{"krate":0,"index":47}},{"kind":"Variable","span":{"file_name":"src/lib.rs","byte_start":772,"byte_end":775,"line_start":37,"line_end":37,"column_start":13,"column_end":16},"ref_id":{"krate":0,"index":4294967237}},{"kind":"Variable","span":{"file_name":"src/lib.rs","byte_start":815,"byte_end":818,"line_start":40,"line_end":40,"column_start":24,"column_end":27},"ref_id":{"krate":0,"index":4294967237}},{"kind":"Variable","span":{"file_name":"src/lib.rs","byte_start":822,"byte_end":826,"line_start":40,"line_end":40,"column_start":31,"column_end":35},"ref_id":{"krate":0,"index":4294967241}},{"kind":"Variable","span":{"file_name":"src/lib.rs","byte_start":827,"byte_end":833,"line_start":40,"line_end":40,"column_start":36,"column_end":42},"ref_id":{"krate":0,"index":47}},{"kind":"Variable","span":{"file_name":"src/lib.rs","byte_start":883,"byte_end":886,"line_start":43,"line_end":43,"column_start":13,"column_end":16},"ref_id":{"krate":0,"index":4294967237}},{"kind":"Variable","span":{"file_name":"src/lib.rs","byte_start":925,"byte_end":931,"line_start":46,"line_end":46,"column_start":23,"column_end":29},"ref_id":{"krate":0,"index":4294967233}},{"kind":"Variable","span":{"file_name":"src/lib.rs","byte_start":951,"byte_end":955,"line_start":47,"line_end":47,"column_start":13,"column_end":17},"ref_id":{"krate":0,"index":4294967241}},{"kind":"Variable","span":{"file_name":"src/lib.rs","byte_start":956,"byte_end":961,"line_start":47,"line_end":47,"column_start":18,"column_end":23},"ref_id":{"krate":0,"index":46}},{"kind":"Variable","span":{"file_name":"src/lib.rs","byte_start":995,"byte_end":1001,"line_start":49,"line_end":49,"column_start":13,"column_end":19},"ref_id":{"krate":0,"index":4294967233}},{"kind":"Variable","span":{"file_name":"src/lib.rs","byte_start":1040,"byte_end":1046,"line_start":52,"line_end":52,"column_start":23,"column_end":29},"ref_id":{"krate":0,"index":4294967233}},{"kind":"Variable","span":{"file_name":"src/lib.rs","byte_start":1050,"byte_end":1054,"line_start":52,"line_end":52,"column_start":33,"column_end":37},"ref_id":{"krate":0,"index":4294967241}},{"kind":"Variable","span":{"file_name":"src/lib.rs","byte_start":1055,"byte_end":1060,"line_start":52,"line_end":52,"column_start":38,"column_end":43},"ref_id":{"krate":0,"index":46}},{"kind":"Variable","span":{"file_name":"src/lib.rs","byte_start":1109,"byte_end":1115,"line_start":55,"line_end":55,"column_start":13,"column_end":19},"ref_id":{"krate":0,"index":4294967233}},{"kind":"Function","span":{"file_name":"src/lib.rs","byte_start":1154,"byte_end":1163,"line_start":58,"line_end":58,"column_start":23,"column_end":32},"ref_id":{"krate":0,"index":7}},{"kind":"Variable","span":{"file_name":"src/lib.rs","byte_start":1149,"byte_end":1153,"line_start":58,"line_end":58,"column_start":18,"column_end":22},"ref_id":{"krate":0,"index":4294967241}},{"kind":"Variable","span":{"file_name":"src/lib.rs","byte_start":1164,"byte_end":1169,"line_start":58,"line_end":58,"column_start":33,"column_end":38},"ref_id":{"krate":0,"index":4294967223}},{"kind":"Variable","span":{"file_name":"src/lib.rs","byte_start":1171,"byte_end":1175,"line_start":58,"line_end":58,"column_start":40,"column_end":44},"ref_id":{"krate":0,"index":4294967185}},{"kind":"Variable","span":{"file_name":"src/lib.rs","byte_start":1186,"byte_end":1191,"line_start":59,"line_end":59,"column_start":9,"column_end":14},"ref_id":{"krate":0,"index":4294967226}},{"kind":"Variable","span":{"file_name":"src/lib.rs","byte_start":1195,"byte_end":1199,"line_start":59,"line_end":59,"column_start":18,"column_end":22},"ref_id":{"krate":0,"index":4294967241}},{"kind":"Variable","span":{"file_name":"src/lib.rs","byte_start":1200,"byte_end":1205,"line_start":59,"line_end":59,"column_start":23,"column_end":28},"ref_id":{"krate":0,"index":48}},{"kind":"Variable","span":{"file_name":"src/lib.rs","byte_start":1206,"byte_end":1208,"line_start":59,"line_end":59,"column_start":29,"column_end":31},"ref_id":{"krate":0,"index":4294967147}},{"kind":"Function","span":{"file_name":"src/lib.rs","byte_start":1239,"byte_end":1248,"line_start":61,"line_end":61,"column_start":22,"column_end":31},"ref_id":{"krate":0,"index":7}},{"kind":"Variable","span":{"file_name":"src/lib.rs","byte_start":1234,"byte_end":1238,"line_start":61,"line_end":61,"column_start":17,"column_end":21},"ref_id":{"krate":0,"index":4294967241}},{"kind":"Variable","span":{"file_name":"src/lib.rs","byte_start":1249,"byte_end":1254,"line_start":61,"line_end":61,"column_start":32,"column_end":37},"ref_id":{"krate":0,"index":4294967223}},{"kind":"Variable","span":{"file_name":"src/lib.rs","byte_start":1256,"byte_end":1262,"line_start":61,"line_end":61,"column_start":39,"column_end":45},"ref_id":{"krate":0,"index":4294967233}},{"kind":"Variable","span":{"file_name":"src/lib.rs","byte_start":1273,"byte_end":1278,"line_start":62,"line_end":62,"column_start":9,"column_end":14},"ref_id":{"krate":0,"index":4294967226}},{"kind":"Variable","span":{"file_name":"src/lib.rs","byte_start":1282,"byte_end":1286,"line_start":62,"line_end":62,"column_start":18,"column_end":22},"ref_id":{"krate":0,"index":4294967241}},{"kind":"Variable","span":{"file_name":"src/lib.rs","byte_start":1287,"byte_end":1292,"line_start":62,"line_end":62,"column_start":23,"column_end":28},"ref_id":{"krate":0,"index":48}},{"kind":"Variable","span":{"file_name":"src/lib.rs","byte_start":1293,"byte_end":1294,"line_start":62,"line_end":62,"column_start":29,"column_end":30},"ref_id":{"krate":0,"index":4294967125}},{"kind":"Function","span":{"file_name":"src/lib.rs","byte_start":1326,"byte_end":1335,"line_start":64,"line_end":64,"column_start":23,"column_end":32},"ref_id":{"krate":0,"index":7}},{"kind":"Variable","span":{"file_name":"src/lib.rs","byte_start":1321,"byte_end":1325,"line_start":64,"line_end":64,"column_start":18,"column_end":22},"ref_id":{"krate":0,"index":4294967241}},{"kind":"Variable","span":{"file_name":"src/lib.rs","byte_start":1336,"byte_end":1341,"line_start":64,"line_end":64,"column_start":33,"column_end":38},"ref_id":{"krate":0,"index":4294967223}},{"kind":"Variable","span":{"file_name":"src/lib.rs","byte_start":1343,"byte_end":1347,"line_start":64,"line_end":64,"column_start":40,"column_end":44},"ref_id":{"krate":0,"index":4294967166}},{"kind":"Variable","span":{"file_name":"src/lib.rs","byte_start":1358,"byte_end":1363,"line_start":65,"line_end":65,"column_start":9,"column_end":14},"ref_id":{"krate":0,"index":4294967226}},{"kind":"Variable","span":{"file_name":"src/lib.rs","byte_start":1367,"byte_end":1371,"line_start":65,"line_end":65,"column_start":18,"column_end":22},"ref_id":{"krate":0,"index":4294967241}},{"kind":"Variable","span":{"file_name":"src/lib.rs","byte_start":1372,"byte_end":1377,"line_start":65,"line_end":65,"column_start":23,"column_end":28},"ref_id":{"krate":0,"index":48}},{"kind":"Variable","span":{"file_name":"src/lib.rs","byte_start":1378,"byte_end":1380,"line_start":65,"line_end":65,"column_start":29,"column_end":31},"ref_id":{"krate":0,"index":4294967103}},{"kind":"Function","span":{"file_name":"src/lib.rs","byte_start":1411,"byte_end":1420,"line_start":67,"line_end":67,"column_start":22,"column_end":31},"ref_id":{"krate":0,"index":7}},{"kind":"Variable","span":{"file_name":"src/lib.rs","byte_start":1406,"byte_end":1410,"line_start":67,"line_end":67,"column_start":17,"column_end":21},"ref_id":{"krate":0,"index":4294967241}},{"kind":"Variable","span":{"file_name":"src/lib.rs","byte_start":1421,"byte_end":1424,"line_start":67,"line_end":67,"column_start":32,"column_end":35},"ref_id":{"krate":0,"index":4294967237}},{"kind":"Variable","span":{"file_name":"src/lib.rs","byte_start":1426,"byte_end":1430,"line_start":67,"line_end":67,"column_start":37,"column_end":41},"ref_id":{"krate":0,"index":4294967185}},{"kind":"Variable","span":{"file_name":"src/lib.rs","byte_start":1441,"byte_end":1446,"line_start":68,"line_end":68,"column_start":9,"column_end":14},"ref_id":{"krate":0,"index":4294967226}},{"kind":"Variable","span":{"file_name":"src/lib.rs","byte_start":1450,"byte_end":1454,"line_start":68,"line_end":68,"column_start":18,"column_end":22},"ref_id":{"krate":0,"index":4294967241}},{"kind":"Variable","span":{"file_name":"src/lib.rs","byte_start":1455,"byte_end":1460,"line_start":68,"line_end":68,"column_start":23,"column_end":28},"ref_id":{"krate":0,"index":48}},{"kind":"Variable","span":{"file_name":"src/lib.rs","byte_start":1461,"byte_end":1462,"line_start":68,"line_end":68,"column_start":29,"column_end":30},"ref_id":{"krate":0,"index":4294967081}},{"kind":"Function","span":{"file_name":"src/lib.rs","byte_start":1493,"byte_end":1502,"line_start":70,"line_end":70,"column_start":22,"column_end":31},"ref_id":{"krate":0,"index":7}},{"kind":"Variable","span":{"file_name":"src/lib.rs","byte_start":1488,"byte_end":1492,"line_start":70,"line_end":70,"column_start":17,"column_end":21},"ref_id":{"krate":0,"index":4294967241}},{"kind":"Variable","span":{"file_name":"src/lib.rs","byte_start":1503,"byte_end":1506,"line_start":70,"line_end":70,"column_start":32,"column_end":35},"ref_id":{"krate":0,"index":4294967237}},{"kind":"Variable","span":{"file_name":"src/lib.rs","byte_start":1508,"byte_end":1512,"line_start":70,"line_end":70,"column_start":37,"column_end":41},"ref_id":{"krate":0,"index":4294967166}},{"kind":"Variable","span":{"file_name":"src/lib.rs","byte_start":1523,"byte_end":1528,"line_start":71,"line_end":71,"column_start":9,"column_end":14},"ref_id":{"krate":0,"index":4294967226}},{"kind":"Variable","span":{"file_name":"src/lib.rs","byte_start":1532,"byte_end":1536,"line_start":71,"line_end":71,"column_start":18,"column_end":22},"ref_id":{"krate":0,"index":4294967241}},{"kind":"Variable","span":{"file_name":"src/lib.rs","byte_start":1537,"byte_end":1542,"line_start":71,"line_end":71,"column_start":23,"column_end":28},"ref_id":{"krate":0,"index":48}},{"kind":"Variable","span":{"file_name":"src/lib.rs","byte_start":1543,"byte_end":1544,"line_start":71,"line_end":71,"column_start":29,"column_end":30},"ref_id":{"krate":0,"index":4294967059}},{"kind":"Function","span":{"file_name":"src/lib.rs","byte_start":1576,"byte_end":1585,"line_start":73,"line_end":73,"column_start":23,"column_end":32},"ref_id":{"krate":0,"index":7}},{"kind":"Variable","span":{"file_name":"src/lib.rs","byte_start":1571,"byte_end":1575,"line_start":73,"line_end":73,"column_start":18,"column_end":22},"ref_id":{"krate":0,"index":4294967241}},{"kind":"Variable","span":{"file_name":"src/lib.rs","byte_start":1586,"byte_end":1591,"line_start":73,"line_end":73,"column_start":33,"column_end":38},"ref_id":{"krate":0,"index":4294967204}},{"kind":"Variable","span":{"file_name":"src/lib.rs","byte_start":1593,"byte_end":1597,"line_start":73,"line_end":73,"column_start":40,"column_end":44},"ref_id":{"krate":0,"index":4294967185}},{"kind":"Variable","span":{"file_name":"src/lib.rs","byte_start":1608,"byte_end":1613,"line_start":74,"line_end":74,"column_start":9,"column_end":14},"ref_id":{"krate":0,"index":4294967226}},{"kind":"Variable","span":{"file_name":"src/lib.rs","byte_start":1617,"byte_end":1621,"line_start":74,"line_end":74,"column_start":18,"column_end":22},"ref_id":{"krate":0,"index":4294967241}},{"kind":"Variable","span":{"file_name":"src/lib.rs","byte_start":1622,"byte_end":1627,"line_start":74,"line_end":74,"column_start":23,"column_end":28},"ref_id":{"krate":0,"index":48}},{"kind":"Variable","span":{"file_name":"src/lib.rs","byte_start":1628,"byte_end":1630,"line_start":74,"line_end":74,"column_start":29,"column_end":31},"ref_id":{"krate":0,"index":4294967037}},{"kind":"Function","span":{"file_name":"src/lib.rs","byte_start":1661,"byte_end":1670,"line_start":76,"line_end":76,"column_start":22,"column_end":31},"ref_id":{"krate":0,"index":7}},{"kind":"Variable","span":{"file_name":"src/lib.rs","byte_start":1656,"byte_end":1660,"line_start":76,"line_end":76,"column_start":17,"column_end":21},"ref_id":{"krate":0,"index":4294967241}},{"kind":"Variable","span":{"file_name":"src/lib.rs","byte_start":1671,"byte_end":1676,"line_start":76,"line_end":76,"column_start":32,"column_end":37},"ref_id":{"krate":0,"index":4294967204}},{"kind":"Variable","span":{"file_name":"src/lib.rs","byte_start":1678,"byte_end":1684,"line_start":76,"line_end":76,"column_start":39,"column_end":45},"ref_id":{"krate":0,"index":4294967233}},{"kind":"Variable","span":{"file_name":"src/lib.rs","byte_start":1695,"byte_end":1700,"line_start":77,"line_end":77,"column_start":9,"column_end":14},"ref_id":{"krate":0,"index":4294967226}},{"kind":"Variable","span":{"file_name":"src/lib.rs","byte_start":1704,"byte_end":1708,"line_start":77,"line_end":77,"column_start":18,"column_end":22},"ref_id":{"krate":0,"index":4294967241}},{"kind":"Variable","span":{"file_name":"src/lib.rs","byte_start":1709,"byte_end":1714,"line_start":77,"line_end":77,"column_start":23,"column_end":28},"ref_id":{"krate":0,"index":48}},{"kind":"Variable","span":{"file_name":"src/lib.rs","byte_start":1715,"byte_end":1716,"line_start":77,"line_end":77,"column_start":29,"column_end":30},"ref_id":{"krate":0,"index":4294967015}},{"kind":"Function","span":{"file_name":"src/lib.rs","byte_start":1748,"byte_end":1757,"line_start":79,"line_end":79,"column_start":23,"column_end":32},"ref_id":{"krate":0,"index":7}},{"kind":"Variable","span":{"file_name":"src/lib.rs","byte_start":1743,"byte_end":1747,"line_start":79,"line_end":79,"column_start":18,"column_end":22},"ref_id":{"krate":0,"index":4294967241}},{"kind":"Variable","span":{"file_name":"src/lib.rs","byte_start":1758,"byte_end":1763,"line_start":79,"line_end":79,"column_start":33,"column_end":38},"ref_id":{"krate":0,"index":4294967204}},{"kind":"Variable","span":{"file_name":"src/lib.rs","byte_start":1765,"byte_end":1769,"line_start":79,"line_end":79,"column_start":40,"column_end":44},"ref_id":{"krate":0,"index":4294967166}},{"kind":"Variable","span":{"file_name":"src/lib.rs","byte_start":1780,"byte_end":1785,"line_start":80,"line_end":80,"column_start":9,"column_end":14},"ref_id":{"krate":0,"index":4294967226}},{"kind":"Variable","span":{"file_name":"src/lib.rs","byte_start":1789,"byte_end":1793,"line_start":80,"line_end":80,"column_start":18,"column_end":22},"ref_id":{"krate":0,"index":4294967241}},{"kind":"Variable","span":{"file_name":"src/lib.rs","byte_start":1794,"byte_end":1799,"line_start":80,"line_end":80,"column_start":23,"column_end":28},"ref_id":{"krate":0,"index":48}},{"kind":"Variable","span":{"file_name":"src/lib.rs","byte_start":1800,"byte_end":1802,"line_start":80,"line_end":80,"column_start":29,"column_end":31},"ref_id":{"krate":0,"index":4294966993}},{"kind":"Variable","span":{"file_name":"src/lib.rs","byte_start":1820,"byte_end":1825,"line_start":82,"line_end":82,"column_start":9,"column_end":14},"ref_id":{"krate":0,"index":4294967226}},{"kind":"Type","span":{"file_name":"src/lib.rs","byte_start":1856,"byte_end":1864,"line_start":87,"line_end":87,"column_start":6,"column_end":14},"ref_id":{"krate":0,"index":45}},{"kind":"Type","span":{"file_name":"src/lib.rs","byte_start":1856,"byte_end":1864,"line_start":87,"line_end":87,"column_start":6,"column_end":14},"ref_id":{"krate":0,"index":45}},{"kind":"Function","span":{"file_name":"src/lib.rs","byte_start":1944,"byte_end":1949,"line_start":90,"line_end":90,"column_start":24,"column_end":29},"ref_id":{"krate":2,"index":2182}},{"kind":"Variable","span":{"file_name":"src/lib.rs","byte_start":1933,"byte_end":1937,"line_start":90,"line_end":90,"column_start":13,"column_end":17},"ref_id":{"krate":0,"index":4294966102}},{"kind":"Variable","span":{"file_name":"src/lib.rs","byte_start":1938,"byte_end":1943,"line_start":90,"line_end":90,"column_start":18,"column_end":23},"ref_id":{"krate":0,"index":48}},{"kind":"Variable","span":{"file_name":"src/lib.rs","byte_start":2000,"byte_end":2004,"line_start":94,"line_end":94,"column_start":27,"column_end":31},"ref_id":{"krate":0,"index":4294966102}},{"kind":"Variable","span":{"file_name":"src/lib.rs","byte_start":2005,"byte_end":2011,"line_start":94,"line_end":94,"column_start":32,"column_end":38},"ref_id":{"krate":0,"index":47}},{"kind":"Variable","span":{"file_name":"src/lib.rs","byte_start":2044,"byte_end":2048,"line_start":95,"line_end":95,"column_start":31,"column_end":35},"ref_id":{"krate":0,"index":4294966102}},{"kind":"Variable","span":{"file_name":"src/lib.rs","byte_start":2049,"byte_end":2054,"line_start":95,"line_end":95,"column_start":36,"column_end":41},"ref_id":{"krate":0,"index":46}},{"kind":"Function","span":{"file_name":"src/lib.rs","byte_start":2092,"byte_end":2101,"line_start":96,"line_end":96,"column_start":36,"column_end":45},"ref_id":{"krate":0,"index":7}},{"kind":"Variable","span":{"file_name":"src/lib.rs","byte_start":2087,"byte_end":2091,"line_start":96,"line_end":96,"column_start":31,"column_end":35},"ref_id":{"krate":0,"index":4294966102}},{"kind":"Variable","span":{"file_name":"src/lib.rs","byte_start":2102,"byte_end":2105,"line_start":96,"line_end":96,"column_start":46,"column_end":49},"ref_id":{"krate":0,"index":4294966037}},{"kind":"Variable","span":{"file_name":"src/lib.rs","byte_start":2107,"byte_end":2110,"line_start":96,"line_end":96,"column_start":51,"column_end":54},"ref_id":{"krate":0,"index":4294966030}},{"kind":"Variable","span":{"file_name":"src/lib.rs","byte_start":2144,"byte_end":2148,"line_start":97,"line_end":97,"column_start":32,"column_end":36},"ref_id":{"krate":0,"index":4294966102}},{"kind":"Variable","span":{"file_name":"src/lib.rs","byte_start":2149,"byte_end":2154,"line_start":97,"line_end":97,"column_start":37,"column_end":42},"ref_id":{"krate":0,"index":48}},{"kind":"Variable","span":{"file_name":"src/lib.rs","byte_start":2155,"byte_end":2158,"line_start":97,"line_end":97,"column_start":43,"column_end":46},"ref_id":{"krate":0,"index":4294966022}},{"kind":"Function","span":{"file_name":"src/lib.rs","byte_start":2207,"byte_end":2226,"line_start":98,"line_end":98,"column_start":47,"column_end":66},"ref_id":{"krate":0,"index":8}},{"kind":"Variable","span":{"file_name":"src/lib.rs","byte_start":2202,"byte_end":2206,"line_start":98,"line_end":98,"column_start":42,"column_end":46},"ref_id":{"krate":0,"index":4294966102}},{"kind":"Variable","span":{"file_name":"src/lib.rs","byte_start":2227,"byte_end":2230,"line_start":98,"line_end":98,"column_start":67,"column_end":70},"ref_id":{"krate":0,"index":4294966037}},{"kind":"Variable","span":{"file_name":"src/lib.rs","byte_start":2232,"byte_end":2235,"line_start":98,"line_end":98,"column_start":72,"column_end":75},"ref_id":{"krate":0,"index":4294966030}},{"kind":"Variable","span":{"file_name":"src/lib.rs","byte_start":2282,"byte_end":2286,"line_start":100,"line_end":100,"column_start":44,"column_end":48},"ref_id":{"krate":0,"index":4294966012}},{"kind":"Variable","span":{"file_name":"src/lib.rs","byte_start":2288,"byte_end":2302,"line_start":100,"line_end":100,"column_start":50,"column_end":64},"ref_id":{"krate":0,"index":4294966004}},{"kind":"Variable","span":{"file_name":"src/lib.rs","byte_start":2390,"byte_end":2395,"line_start":102,"line_end":102,"column_start":32,"column_end":37},"ref_id":{"krate":0,"index":32}},{"kind":"Type","span":{"file_name":"src/lib.rs","byte_start":2384,"byte_end":2388,"line_start":102,"line_end":102,"column_start":26,"column_end":30},"ref_id":{"krate":0,"index":27}},{"kind":"Variable","span":{"file_name":"src/lib.rs","byte_start":2390,"byte_end":2395,"line_start":102,"line_end":102,"column_start":32,"column_end":37},"ref_id":{"krate":0,"index":32}},{"kind":"Type","span":{"file_name":"src/lib.rs","byte_start":2384,"byte_end":2388,"line_start":102,"line_end":102,"column_start":26,"column_end":30},"ref_id":{"krate":0,"index":27}},{"kind":"Variable","span":{"file_name":"src/lib.rs","byte_start":2403,"byte_end":2404,"line_start":102,"line_end":102,"column_start":45,"column_end":46},"ref_id":{"krate":0,"index":4294965983}},{"kind":"Variable","span":{"file_name":"src/lib.rs","byte_start":2418,"byte_end":2422,"line_start":102,"line_end":102,"column_start":60,"column_end":64},"ref_id":{"krate":0,"index":29}},{"kind":"Type","span":{"file_name":"src/lib.rs","byte_start":2412,"byte_end":2416,"line_start":102,"line_end":102,"column_start":54,"column_end":58},"ref_id":{"krate":0,"index":27}},{"kind":"Variable","span":{"file_name":"src/lib.rs","byte_start":2509,"byte_end":2514,"line_start":104,"line_end":104,"column_start":32,"column_end":37},"ref_id":{"krate":0,"index":32}},{"kind":"Type","span":{"file_name":"src/lib.rs","byte_start":2503,"byte_end":2507,"line_start":104,"line_end":104,"column_start":26,"column_end":30},"ref_id":{"krate":0,"index":27}},{"kind":"Variable","span":{"file_name":"src/lib.rs","byte_start":2528,"byte_end":2533,"line_start":104,"line_end":104,"column_start":51,"column_end":56},"ref_id":{"krate":0,"index":32}},{"kind":"Type","span":{"file_name":"src/lib.rs","byte_start":2522,"byte_end":2526,"line_start":104,"line_end":104,"column_start":45,"column_end":49},"ref_id":{"krate":0,"index":27}},{"kind":"Variable","span":{"file_name":"src/lib.rs","byte_start":2509,"byte_end":2514,"line_start":104,"line_end":104,"column_start":32,"column_end":37},"ref_id":{"krate":0,"index":32}},{"kind":"Type","span":{"file_name":"src/lib.rs","byte_start":2503,"byte_end":2507,"line_start":104,"line_end":104,"column_start":26,"column_end":30},"ref_id":{"krate":0,"index":27}},{"kind":"Variable","span":{"file_name":"src/lib.rs","byte_start":2528,"byte_end":2533,"line_start":104,"line_end":104,"column_start":51,"column_end":56},"ref_id":{"krate":0,"index":32}},{"kind":"Type","span":{"file_name":"src/lib.rs","byte_start":2522,"byte_end":2526,"line_start":104,"line_end":104,"column_start":45,"column_end":49},"ref_id":{"krate":0,"index":27}},{"kind":"Variable","span":{"file_name":"src/lib.rs","byte_start":2547,"byte_end":2552,"line_start":104,"line_end":104,"column_start":70,"column_end":75},"ref_id":{"krate":0,"index":32}},{"kind":"Type","span":{"file_name":"src/lib.rs","byte_start":2541,"byte_end":2545,"line_start":104,"line_end":104,"column_start":64,"column_end":68},"ref_id":{"krate":0,"index":27}},{"kind":"Variable","span":{"file_name":"src/lib.rs","byte_start":2638,"byte_end":2643,"line_start":106,"line_end":106,"column_start":32,"column_end":37},"ref_id":{"krate":0,"index":32}},{"kind":"Type","span":{"file_name":"src/lib.rs","byte_start":2632,"byte_end":2636,"line_start":106,"line_end":106,"column_start":26,"column_end":30},"ref_id":{"krate":0,"index":27}},{"kind":"Variable","span":{"file_name":"src/lib.rs","byte_start":2638,"byte_end":2643,"line_start":106,"line_end":106,"column_start":32,"column_end":37},"ref_id":{"krate":0,"index":32}},{"kind":"Type","span":{"file_name":"src/lib.rs","byte_start":2632,"byte_end":2636,"line_start":106,"line_end":106,"column_start":26,"column_end":30},"ref_id":{"krate":0,"index":27}},{"kind":"Variable","span":{"file_name":"src/lib.rs","byte_start":2651,"byte_end":2652,"line_start":106,"line_end":106,"column_start":45,"column_end":46},"ref_id":{"krate":0,"index":4294965953}},{"kind":"Variable","span":{"file_name":"src/lib.rs","byte_start":2666,"byte_end":2670,"line_start":106,"line_end":106,"column_start":60,"column_end":64},"ref_id":{"krate":0,"index":29}},{"kind":"Type","span":{"file_name":"src/lib.rs","byte_start":2660,"byte_end":2664,"line_start":106,"line_end":106,"column_start":54,"column_end":58},"ref_id":{"krate":0,"index":27}},{"kind":"Variable","span":{"file_name":"src/lib.rs","byte_start":2755,"byte_end":2759,"line_start":108,"line_end":108,"column_start":32,"column_end":36},"ref_id":{"krate":0,"index":29}},{"kind":"Type","span":{"file_name":"src/lib.rs","byte_start":2749,"byte_end":2753,"line_start":108,"line_end":108,"column_start":26,"column_end":30},"ref_id":{"krate":0,"index":27}},{"kind":"Variable","span":{"file_name":"src/lib.rs","byte_start":2755,"byte_end":2759,"line_start":108,"line_end":108,"column_start":32,"column_end":36},"ref_id":{"krate":0,"index":29}},{"kind":"Type","span":{"file_name":"src/lib.rs","byte_start":2749,"byte_end":2753,"line_start":108,"line_end":108,"column_start":26,"column_end":30},"ref_id":{"krate":0,"index":27}},{"kind":"Variable","span":{"file_name":"src/lib.rs","byte_start":2773,"byte_end":2778,"line_start":108,"line_end":108,"column_start":50,"column_end":55},"ref_id":{"krate":0,"index":32}},{"kind":"Type","span":{"file_name":"src/lib.rs","byte_start":2767,"byte_end":2771,"line_start":108,"line_end":108,"column_start":44,"column_end":48},"ref_id":{"krate":0,"index":27}},{"kind":"Variable","span":{"file_name":"src/lib.rs","byte_start":2884,"byte_end":2893,"line_start":110,"line_end":110,"column_start":43,"column_end":52},"ref_id":{"krate":0,"index":4294965933}},{"kind":"Variable","span":{"file_name":"src/lib.rs","byte_start":2939,"byte_end":2943,"line_start":113,"line_end":113,"column_start":21,"column_end":25},"ref_id":{"krate":0,"index":4294966046}},{"kind":"Variable","span":{"file_name":"src/lib.rs","byte_start":2944,"byte_end":2947,"line_start":113,"line_end":113,"column_start":26,"column_end":29},"ref_id":{"krate":0,"index":4294966022}},{"kind":"Variable","span":{"file_name":"src/lib.rs","byte_start":2951,"byte_end":2960,"line_start":113,"line_end":113,"column_start":33,"column_end":42},"ref_id":{"krate":0,"index":4294965994}},{"kind":"Variable","span":{"file_name":"src/lib.rs","byte_start":3013,"byte_end":3017,"line_start":118,"line_end":118,"column_start":9,"column_end":13},"ref_id":{"krate":0,"index":4294966102}},{"kind":"Variable","span":{"file_name":"src/lib.rs","byte_start":3018,"byte_end":3023,"line_start":118,"line_end":118,"column_start":14,"column_end":19},"ref_id":{"krate":0,"index":48}},{"kind":"Variable","span":{"file_name":"src/lib.rs","byte_start":3026,"byte_end":3030,"line_start":118,"line_end":118,"column_start":22,"column_end":26},"ref_id":{"krate":0,"index":4294966046}},{"kind":"Type","span":{"file_name":"src/lib.rs","byte_start":1856,"byte_end":1864,"line_start":87,"line_end":87,"column_start":6,"column_end":14},"ref_id":{"krate":0,"index":45}},{"kind":"Function","span":{"file_name":"src/lib.rs","byte_start":3121,"byte_end":3130,"line_start":122,"line_end":122,"column_start":24,"column_end":33},"ref_id":{"krate":0,"index":7}},{"kind":"Variable","span":{"file_name":"src/lib.rs","byte_start":3116,"byte_end":3120,"line_start":122,"line_end":122,"column_start":19,"column_end":23},"ref_id":{"krate":0,"index":4294965909}},{"kind":"Variable","span":{"file_name":"src/lib.rs","byte_start":3131,"byte_end":3134,"line_start":122,"line_end":122,"column_start":34,"column_end":37},"ref_id":{"krate":0,"index":4294965905}},{"kind":"Variable","span":{"file_name":"src/lib.rs","byte_start":3136,"byte_end":3142,"line_start":122,"line_end":122,"column_start":39,"column_end":45},"ref_id":{"krate":0,"index":4294965901}},{"kind":"Function","span":{"file_name":"src/lib.rs","byte_start":3169,"byte_end":3175,"line_start":123,"line_end":123,"column_start":25,"column_end":31},"ref_id":{"krate":0,"index":13}},{"kind":"Variable","span":{"file_name":"src/lib.rs","byte_start":3153,"byte_end":3157,"line_start":123,"line_end":123,"column_start":9,"column_end":13},"ref_id":{"krate":0,"index":4294965909}},{"kind":"Variable","span":{"file_name":"src/lib.rs","byte_start":3158,"byte_end":3163,"line_start":123,"line_end":123,"column_start":14,"column_end":19},"ref_id":{"krate":0,"index":48}},{"kind":"Variable","span":{"file_name":"src/lib.rs","byte_start":3164,"byte_end":3167,"line_start":123,"line_end":123,"column_start":20,"column_end":23},"ref_id":{"krate":0,"index":4294965795}},{"kind":"Type","span":{"file_name":"src/lib.rs","byte_start":3206,"byte_end":3214,"line_start":126,"line_end":126,"column_start":21,"column_end":29},"ref_id":{"krate":0,"index":45}},{"kind":"Function","span":{"file_name":"src/lib.rs","byte_start":3197,"byte_end":3200,"line_start":126,"line_end":126,"column_start":12,"column_end":15},"ref_id":{"krate":0,"index":85}},{"kind":"Type","span":{"file_name":"src/lib.rs","byte_start":1856,"byte_end":1864,"line_start":87,"line_end":87,"column_start":6,"column_end":14},"ref_id":{"krate":0,"index":45}},{"kind":"Type","span":{"file_name":"src/lib.rs","byte_start":3206,"byte_end":3214,"line_start":126,"line_end":126,"column_start":21,"column_end":29},"ref_id":{"krate":0,"index":45}},{"kind":"Function","span":{"file_name":"src/lib.rs","byte_start":3232,"byte_end":3246,"line_start":127,"line_end":127,"column_start":16,"column_end":30},"ref_id":{"krate":0,"index":4}},{"kind":"Mod","span":{"file_name":"src/lib.rs","byte_start":3225,"byte_end":3230,"line_start":127,"line_end":127,"column_start":9,"column_end":14},"ref_id":{"krate":0,"index":3}},{"kind":"Function","span":{"file_name":"src/lib.rs","byte_start":3546,"byte_end":3553,"line_start":140,"line_end":140,"column_start":14,"column_end":21},"ref_id":{"krate":2,"index":3704}},{"kind":"Function","span":{"file_name":"src/lib.rs","byte_start":3356,"byte_end":3359,"line_start":133,"line_end":133,"column_start":14,"column_end":17},"ref_id":{"krate":2,"index":3669}},{"kind":"Variable","span":{"file_name":"src/lib.rs","byte_start":3327,"byte_end":3332,"line_start":132,"line_end":132,"column_start":25,"column_end":30},"ref_id":{"krate":0,"index":4294965740}},{"kind":"Variable","span":{"file_name":"src/lib.rs","byte_start":3335,"byte_end":3341,"line_start":132,"line_end":132,"column_start":33,"column_end":39},"ref_id":{"krate":0,"index":4294965737}},{"kind":"Variable","span":{"file_name":"src/lib.rs","byte_start":3385,"byte_end":3386,"line_start":134,"line_end":134,"column_start":20,"column_end":21},"ref_id":{"krate":0,"index":4294965723}},{"kind":"Variable","span":{"file_name":"src/lib.rs","byte_start":3399,"byte_end":3400,"line_start":134,"line_end":134,"column_start":34,"column_end":35},"ref_id":{"krate":0,"index":4294965723}},{"kind":"Variable","span":{"file_name":"src/lib.rs","byte_start":3438,"byte_end":3443,"line_start":135,"line_end":135,"column_start":27,"column_end":32},"ref_id":{"krate":0,"index":32}},{"kind":"Type","span":{"file_name":"src/lib.rs","byte_start":3432,"byte_end":3436,"line_start":135,"line_end":135,"column_start":21,"column_end":25},"ref_id":{"krate":0,"index":27}},{"kind":"Variable","span":{"file_name":"src/lib.rs","byte_start":3495,"byte_end":3499,"line_start":137,"line_end":137,"column_start":27,"column_end":31},"ref_id":{"krate":0,"index":29}},{"kind":"Type","span":{"file_name":"src/lib.rs","byte_start":3489,"byte_end":3493,"line_start":137,"line_end":137,"column_start":21,"column_end":25},"ref_id":{"krate":0,"index":27}},{"kind":"Type","span":{"file_name":"src/lib.rs","byte_start":3566,"byte_end":3574,"line_start":142,"line_end":142,"column_start":9,"column_end":17},"ref_id":{"krate":0,"index":45}},{"kind":"Variable","span":{"file_name":"src/lib.rs","byte_start":3589,"byte_end":3594,"line_start":143,"line_end":143,"column_start":13,"column_end":18},"ref_id":{"krate":0,"index":46}},{"kind":"Variable","span":{"file_name":"src/lib.rs","byte_start":3589,"byte_end":3594,"line_start":143,"line_end":143,"column_start":13,"column_end":18},"ref_id":{"krate":0,"index":4294965740}},{"kind":"Variable","span":{"file_name":"src/lib.rs","byte_start":3608,"byte_end":3614,"line_start":144,"line_end":144,"column_start":13,"column_end":19},"ref_id":{"krate":0,"index":47}},{"kind":"Variable","span":{"file_name":"src/lib.rs","byte_start":3608,"byte_end":3614,"line_start":144,"line_end":144,"column_start":13,"column_end":19},"ref_id":{"krate":0,"index":4294965737}},{"kind":"Variable","span":{"file_name":"src/lib.rs","byte_start":3628,"byte_end":3633,"line_start":145,"line_end":145,"column_start":13,"column_end":18},"ref_id":{"krate":0,"index":48}},{"kind":"Variable","span":{"file_name":"src/lib.rs","byte_start":3628,"byte_end":3633,"line_start":145,"line_end":145,"column_start":13,"column_end":18},"ref_id":{"krate":0,"index":4294965734}},{"kind":"Type","span":{"file_name":"src/lib.rs","byte_start":1856,"byte_end":1864,"line_start":87,"line_end":87,"column_start":6,"column_end":14},"ref_id":{"krate":0,"index":45}},{"kind":"Variable","span":{"file_name":"src/lib.rs","byte_start":3693,"byte_end":3697,"line_start":150,"line_end":150,"column_start":9,"column_end":13},"ref_id":{"krate":0,"index":4294965680}},{"kind":"Variable","span":{"file_name":"src/lib.rs","byte_start":3698,"byte_end":3703,"line_start":150,"line_end":150,"column_start":14,"column_end":19},"ref_id":{"krate":0,"index":46}},{"kind":"Type","span":{"file_name":"src/lib.rs","byte_start":1856,"byte_end":1864,"line_start":87,"line_end":87,"column_start":6,"column_end":14},"ref_id":{"krate":0,"index":45}},{"kind":"Variable","span":{"file_name":"src/lib.rs","byte_start":3753,"byte_end":3757,"line_start":154,"line_end":154,"column_start":9,"column_end":13},"ref_id":{"krate":0,"index":4294965616}},{"kind":"Variable","span":{"file_name":"src/lib.rs","byte_start":3758,"byte_end":3764,"line_start":154,"line_end":154,"column_start":14,"column_end":20},"ref_id":{"krate":0,"index":47}},{"kind":"Type","span":{"file_name":"src/lib.rs","byte_start":3806,"byte_end":3810,"line_start":157,"line_end":157,"column_start":35,"column_end":39},"ref_id":{"krate":0,"index":27}},{"kind":"Type","span":{"file_name":"src/lib.rs","byte_start":1856,"byte_end":1864,"line_start":87,"line_end":87,"column_start":6,"column_end":14},"ref_id":{"krate":0,"index":45}},{"kind":"Type","span":{"file_name":"src/lib.rs","byte_start":3806,"byte_end":3810,"line_start":157,"line_end":157,"column_start":35,"column_end":39},"ref_id":{"krate":0,"index":27}},{"kind":"Function","span":{"file_name":"src/lib.rs","byte_start":3832,"byte_end":3838,"line_start":158,"line_end":158,"column_start":20,"column_end":26},"ref_id":{"krate":5,"index":3867}},{"kind":"Variable","span":{"file_name":"src/lib.rs","byte_start":3821,"byte_end":3825,"line_start":158,"line_end":158,"column_start":9,"column_end":13},"ref_id":{"krate":0,"index":4294965552}},{"kind":"Variable","span":{"file_name":"src/lib.rs","byte_start":3826,"byte_end":3831,"line_start":158,"line_end":158,"column_start":14,"column_end":19},"ref_id":{"krate":0,"index":48}},{"kind":"Type","span":{"file_name":"src/lib.rs","byte_start":1856,"byte_end":1864,"line_start":87,"line_end":87,"column_start":6,"column_end":14},"ref_id":{"krate":0,"index":45}},{"kind":"Variable","span":{"file_name":"src/lib.rs","byte_start":3902,"byte_end":3906,"line_start":162,"line_end":162,"column_start":9,"column_end":13},"ref_id":{"krate":0,"index":4294965483}},{"kind":"Variable","span":{"file_name":"src/lib.rs","byte_start":3907,"byte_end":3912,"line_start":162,"line_end":162,"column_start":14,"column_end":19},"ref_id":{"krate":0,"index":46}},{"kind":"Variable","span":{"file_name":"src/lib.rs","byte_start":3915,"byte_end":3920,"line_start":162,"line_end":162,"column_start":22,"column_end":27},"ref_id":{"krate":0,"index":4294965479}},{"kind":"Variable","span":{"file_name":"src/lib.rs","byte_start":3930,"byte_end":3934,"line_start":163,"line_end":163,"column_start":9,"column_end":13},"ref_id":{"krate":0,"index":4294965483}},{"kind":"Variable","span":{"file_name":"src/lib.rs","byte_start":3935,"byte_end":3940,"line_start":163,"line_end":163,"column_start":14,"column_end":19},"ref_id":{"krate":0,"index":48}},{"kind":"Function","span":{"file_name":"src/lib.rs","byte_start":3989,"byte_end":3996,"line_start":163,"line_end":163,"column_start":68,"column_end":75},"ref_id":{"krate":2,"index":3704}},{"kind":"Function","span":{"file_name":"src/lib.rs","byte_start":3968,"byte_end":3971,"line_start":163,"line_end":163,"column_start":47,"column_end":50},"ref_id":{"krate":2,"index":3669}},{"kind":"Variable","span":{"file_name":"src/lib.rs","byte_start":3947,"byte_end":3952,"line_start":163,"line_end":163,"column_start":26,"column_end":31},"ref_id":{"krate":0,"index":4294965479}},{"kind":"Variable","span":{"file_name":"src/lib.rs","byte_start":3955,"byte_end":3959,"line_start":163,"line_end":163,"column_start":34,"column_end":38},"ref_id":{"krate":0,"index":4294965483}},{"kind":"Variable","span":{"file_name":"src/lib.rs","byte_start":3960,"byte_end":3966,"line_start":163,"line_end":163,"column_start":39,"column_end":45},"ref_id":{"krate":0,"index":47}},{"kind":"Variable","span":{"file_name":"src/lib.rs","byte_start":3983,"byte_end":3987,"line_start":163,"line_end":163,"column_start":62,"column_end":66},"ref_id":{"krate":0,"index":29}},{"kind":"Type","span":{"file_name":"src/lib.rs","byte_start":3977,"byte_end":3981,"line_start":163,"line_end":163,"column_start":56,"column_end":60},"ref_id":{"krate":0,"index":27}},{"kind":"Type","span":{"file_name":"src/lib.rs","byte_start":1856,"byte_end":1864,"line_start":87,"line_end":87,"column_start":6,"column_end":14},"ref_id":{"krate":0,"index":45}},{"kind":"Variable","span":{"file_name":"src/lib.rs","byte_start":4063,"byte_end":4067,"line_start":167,"line_end":167,"column_start":9,"column_end":13},"ref_id":{"krate":0,"index":4294965368}},{"kind":"Variable","span":{"file_name":"src/lib.rs","byte_start":4068,"byte_end":4074,"line_start":167,"line_end":167,"column_start":14,"column_end":20},"ref_id":{"krate":0,"index":47}},{"kind":"Variable","span":{"file_name":"src/lib.rs","byte_start":4077,"byte_end":4083,"line_start":167,"line_end":167,"column_start":23,"column_end":29},"ref_id":{"krate":0,"index":4294965364}},{"kind":"Variable","span":{"file_name":"src/lib.rs","byte_start":4093,"byte_end":4097,"line_start":168,"line_end":168,"column_start":9,"column_end":13},"ref_id":{"krate":0,"index":4294965368}},{"kind":"Variable","span":{"file_name":"src/lib.rs","byte_start":4098,"byte_end":4103,"line_start":168,"line_end":168,"column_start":14,"column_end":19},"ref_id":{"krate":0,"index":48}},{"kind":"Function","span":{"file_name":"src/lib.rs","byte_start":4152,"byte_end":4159,"line_start":168,"line_end":168,"column_start":68,"column_end":75},"ref_id":{"krate":2,"index":3704}},{"kind":"Function","span":{"file_name":"src/lib.rs","byte_start":4131,"byte_end":4134,"line_start":168,"line_end":168,"column_start":47,"column_end":50},"ref_id":{"krate":2,"index":3669}},{"kind":"Variable","span":{"file_name":"src/lib.rs","byte_start":4110,"byte_end":4114,"line_start":168,"line_end":168,"column_start":26,"column_end":30},"ref_id":{"krate":0,"index":4294965368}},{"kind":"Variable","span":{"file_name":"src/lib.rs","byte_start":4115,"byte_end":4120,"line_start":168,"line_end":168,"column_start":31,"column_end":36},"ref_id":{"krate":0,"index":46}},{"kind":"Variable","span":{"file_name":"src/lib.rs","byte_start":4123,"byte_end":4129,"line_start":168,"line_end":168,"column_start":39,"column_end":45},"ref_id":{"krate":0,"index":4294965364}},{"kind":"Variable","span":{"file_name":"src/lib.rs","byte_start":4146,"byte_end":4150,"line_start":168,"line_end":168,"column_start":62,"column_end":66},"ref_id":{"krate":0,"index":29}},{"kind":"Type","span":{"file_name":"src/lib.rs","byte_start":4140,"byte_end":4144,"line_start":168,"line_end":168,"column_start":56,"column_end":60},"ref_id":{"krate":0,"index":27}},{"kind":"Type","span":{"file_name":"src/lib.rs","byte_start":4177,"byte_end":4185,"line_start":172,"line_end":172,"column_start":6,"column_end":14},"ref_id":{"krate":0,"index":45}},{"kind":"Type","span":{"file_name":"src/lib.rs","byte_start":4221,"byte_end":4225,"line_start":173,"line_end":173,"column_start":34,"column_end":38},"ref_id":{"krate":0,"index":27}},{"kind":"Variable","span":{"file_name":"src/lib.rs","byte_start":4238,"byte_end":4242,"line_start":174,"line_end":174,"column_start":10,"column_end":14},"ref_id":{"krate":0,"index":4294966965}},{"kind":"Variable","span":{"file_name":"src/lib.rs","byte_start":4243,"byte_end":4248,"line_start":174,"line_end":174,"column_start":15,"column_end":20},"ref_id":{"krate":0,"index":48}},{"kind":"Function","span":{"file_name":"src/lib.rs","byte_start":4351,"byte_end":4357,"line_start":178,"line_end":178,"column_start":40,"column_end":46},"ref_id":{"krate":2,"index":3856}},{"kind":"Function","span":{"file_name":"src/lib.rs","byte_start":4344,"byte_end":4348,"line_start":178,"line_end":178,"column_start":33,"column_end":37},"ref_id":{"krate":2,"index":5821}},{"kind":"Variable","span":{"file_name":"src/lib.rs","byte_start":4338,"byte_end":4343,"line_start":178,"line_end":178,"column_start":27,"column_end":32},"ref_id":{"krate":0,"index":4294966947}},{"kind":"Function","span":{"file_name":"src/lib.rs","byte_start":4389,"byte_end":4398,"line_start":179,"line_end":179,"column_start":28,"column_end":37},"ref_id":{"krate":0,"index":7}},{"kind":"Variable","span":{"file_name":"src/lib.rs","byte_start":4384,"byte_end":4388,"line_start":179,"line_end":179,"column_start":23,"column_end":27},"ref_id":{"krate":0,"index":4294966951}},{"kind":"Variable","span":{"file_name":"src/lib.rs","byte_start":4399,"byte_end":4402,"line_start":179,"line_end":179,"column_start":38,"column_end":41},"ref_id":{"krate":0,"index":4294966937}},{"kind":"Variable","span":{"file_name":"src/lib.rs","byte_start":4404,"byte_end":4407,"line_start":179,"line_end":179,"column_start":43,"column_end":46},"ref_id":{"krate":0,"index":4294966936}},{"kind":"Variable","span":{"file_name":"src/lib.rs","byte_start":4422,"byte_end":4426,"line_start":180,"line_end":180,"column_start":13,"column_end":17},"ref_id":{"krate":0,"index":4294966951}},{"kind":"Variable","span":{"file_name":"src/lib.rs","byte_start":4427,"byte_end":4432,"line_start":180,"line_end":180,"column_start":18,"column_end":23},"ref_id":{"krate":0,"index":48}},{"kind":"Variable","span":{"file_name":"src/lib.rs","byte_start":4433,"byte_end":4436,"line_start":180,"line_end":180,"column_start":24,"column_end":27},"ref_id":{"krate":0,"index":4294966927}},{"kind":"Variable","span":{"file_name":"src/lib.rs","byte_start":4446,"byte_end":4451,"line_start":180,"line_end":180,"column_start":37,"column_end":42},"ref_id":{"krate":0,"index":32}},{"kind":"Type","span":{"file_name":"src/lib.rs","byte_start":4440,"byte_end":4444,"line_start":180,"line_end":180,"column_start":31,"column_end":35},"ref_id":{"krate":0,"index":27}},{"kind":"Type","span":{"file_name":"src/lib.rs","byte_start":4477,"byte_end":4481,"line_start":185,"line_end":185,"column_start":6,"column_end":10},"ref_id":{"krate":0,"index":27}},{"kind":"Variable","span":{"file_name":"src/lib.rs","byte_start":4520,"byte_end":4524,"line_start":187,"line_end":187,"column_start":10,"column_end":14},"ref_id":{"krate":0,"index":4294966902}},{"kind":"Variable","span":{"file_name":"src/lib.rs","byte_start":4534,"byte_end":4538,"line_start":187,"line_end":187,"column_start":24,"column_end":28},"ref_id":{"krate":0,"index":4294966902}},{"kind":"Variable","span":{"file_name":"src/lib.rs","byte_start":4559,"byte_end":4563,"line_start":188,"line_end":188,"column_start":19,"column_end":23},"ref_id":{"krate":0,"index":29}},{"kind":"Type","span":{"file_name":"src/lib.rs","byte_start":4553,"byte_end":4557,"line_start":188,"line_end":188,"column_start":13,"column_end":17},"ref_id":{"krate":0,"index":27}},{"kind":"Variable","span":{"file_name":"src/lib.rs","byte_start":4559,"byte_end":4563,"line_start":188,"line_end":188,"column_start":19,"column_end":23},"ref_id":{"krate":0,"index":29}},{"kind":"Type","span":{"file_name":"src/lib.rs","byte_start":4553,"byte_end":4557,"line_start":188,"line_end":188,"column_start":13,"column_end":17},"ref_id":{"krate":0,"index":27}},{"kind":"Variable","span":{"file_name":"src/lib.rs","byte_start":4573,"byte_end":4578,"line_start":188,"line_end":188,"column_start":33,"column_end":38},"ref_id":{"krate":0,"index":32}},{"kind":"Type","span":{"file_name":"src/lib.rs","byte_start":4567,"byte_end":4571,"line_start":188,"line_end":188,"column_start":27,"column_end":31},"ref_id":{"krate":0,"index":27}},{"kind":"Variable","span":{"file_name":"src/lib.rs","byte_start":4598,"byte_end":4603,"line_start":189,"line_end":189,"column_start":19,"column_end":24},"ref_id":{"krate":0,"index":32}},{"kind":"Type","span":{"file_name":"src/lib.rs","byte_start":4592,"byte_end":4596,"line_start":189,"line_end":189,"column_start":13,"column_end":17},"ref_id":{"krate":0,"index":27}},{"kind":"Variable","span":{"file_name":"src/lib.rs","byte_start":4598,"byte_end":4603,"line_start":189,"line_end":189,"column_start":19,"column_end":24},"ref_id":{"krate":0,"index":32}},{"kind":"Type","span":{"file_name":"src/lib.rs","byte_start":4592,"byte_end":4596,"line_start":189,"line_end":189,"column_start":13,"column_end":17},"ref_id":{"krate":0,"index":27}},{"kind":"Variable","span":{"file_name":"src/lib.rs","byte_start":4613,"byte_end":4617,"line_start":189,"line_end":189,"column_start":34,"column_end":38},"ref_id":{"krate":0,"index":29}},{"kind":"Type","span":{"file_name":"src/lib.rs","byte_start":4607,"byte_end":4611,"line_start":189,"line_end":189,"column_start":28,"column_end":32},"ref_id":{"krate":0,"index":27}}],"macro_refs":[],"relations":[{"span":{"file_name":"src/lib.rs","byte_start":467,"byte_end":475,"line_start":26,"line_end":26,"column_start":6,"column_end":14},"kind":{"Impl":{"id":12}},"from":{"krate":0,"index":45},"to":{"krate":4294967295,"index":4294967295}},{"span":{"file_name":"src/lib.rs","byte_start":1856,"byte_end":1864,"line_start":87,"line_end":87,"column_start":6,"column_end":14},"kind":{"Impl":{"id":13}},"from":{"krate":0,"index":45},"to":{"krate":4294967295,"index":4294967295}},{"span":{"file_name":"src/lib.rs","byte_start":4177,"byte_end":4185,"line_start":172,"line_end":172,"column_start":6,"column_end":14},"kind":{"Impl":{"id":14}},"from":{"krate":0,"index":45},"to":{"krate":4294967295,"index":4294967295}},{"span":{"file_name":"src/lib.rs","byte_start":4477,"byte_end":4481,"line_start":185,"line_end":185,"column_start":6,"column_end":10},"kind":{"Impl":{"id":15}},"from":{"krate":0,"index":27},"to":{"krate":4294967295,"index":4294967295}}]}